molecule_lxd/__init__.py
molecule_lxd/driver.py
molecule_lxd/cookiecutter/cookiecutter.json
molecule_lxd/cookiecutter/{{cookiecutter.molecule_directory}}/{{cookiecutter.scenario_name}}/converge.yml
molecule_lxd/playbooks/create.yml
molecule_lxd/playbooks/destroy.yml
molecule_lxd/playbooks/prepare.yml
molecule_lxd/test/__init__.py
molecule_lxd/test/conftest.py
molecule_lxd/test/test_driver.py
molecule_lxd/test/test_func.py
molecule_lxd-0.3.dist-info/LICENSE
molecule_lxd-0.3.dist-info/METADATA
molecule_lxd-0.3.dist-info/WHEEL
molecule_lxd-0.3.dist-info/entry_points.txt
molecule_lxd-0.3.dist-info/top_level.txt
molecule_lxd-0.3.dist-info/RECORD
