Metadata-Version: 2.1
Name: molecule-lxd
Version: 0.3
Summary: LCD Molecule Plugin :: run molecule tests on LXD
Home-page: https://github.com/ansible-community/molecule-lxd
Author: Ansible by Red Hat
Author-email: info@ansible.com
Maintainer: Ansible by Red Hat
Maintainer-email: info@ansible.com
License: MIT
Project-URL: Bug Tracker, https://github.com/ansible-community/molecule-lxd/issues
Project-URL: CI, https://github.com/ansible-community/molecule-lxd/actions
Project-URL: Mailing lists, https://docs.ansible.com/ansible/latest/community/communication.html#mailing-list-information
Project-URL: Source Code, https://github.com/ansible-community/molecule-lxd
Keywords: ansible,roles,testing,molecule,plugin,lxd
Platform: UNKNOWN
Classifier: Development Status :: 2 - Pre-Alpha
Classifier: Environment :: Console
Classifier: Framework :: Pytest
Classifier: Intended Audience :: Developers
Classifier: Intended Audience :: Information Technology
Classifier: Intended Audience :: System Administrators
Classifier: License :: OSI Approved :: MIT License
Classifier: Natural Language :: English
Classifier: Operating System :: OS Independent
Classifier: Programming Language :: Python :: 3
Classifier: Programming Language :: Python :: 3.6
Classifier: Programming Language :: Python :: 3.7
Classifier: Programming Language :: Python :: 3.8
Classifier: Programming Language :: Python :: 3.9
Classifier: Topic :: System :: Systems Administration
Classifier: Topic :: Utilities
Requires-Python: >=3.6
License-File: LICENSE
Requires-Dist: molecule (>=3.2.0)
Requires-Dist: pyyaml (<6,>=5.1)
Provides-Extra: test
Requires-Dist: molecule[test] ; extra == 'test'
